postoi_back/__init__.py
postoi_back/app/API.py
postoi_back/app/Assembly.py
postoi_back/app/Errors.py
postoi_back/app/Exceptions.py
postoi_back/app/Form.py
postoi_back/app/FormElems.py
postoi_back/app/StateHistory.py
postoi_back/app/StateMachine.py
postoi_back/app/Types.py
postoi_back/app/APIs/Messages.py
postoi_back/app/APIs/MonoAPI.py
postoi_back/app/APIs/__init__.py
postoi_back/app/Factories/APIFactory.py
postoi_back/app/Factories/ActiveUsersFactory.py
postoi_back/app/Factories/FormElemFactory.py
postoi_back/app/Factories/FormFactory.py
postoi_back/app/Factories/StorageFactory.py
postoi_back/app/Factories/__init__.py
postoi_back/app/Interface/Form.py
postoi_back/app/Interface/FormElem.py
postoi_back/app/Interface/__init__.py
postoi_back/app/Storage/ActiveUsers.py
postoi_back/app/Storage/Context.py
postoi_back/app/Storage/Models.py
postoi_back/app/Storage/Storage.py
postoi_back/app/Storage/StorageInterface.py
postoi_back/app/Storage/__init__.py
postoi_back-0.1.2.dist-info/METADATA
postoi_back-0.1.2.dist-info/WHEEL
postoi_back-0.1.2.dist-info/top_level.txt
postoi_back-0.1.2.dist-info/RECORD
