Metadata-Version: 2.4
Name: postoi-back
Version: 0.1.2
Summary: Bot logic (state machine) for the Telegram bot
License: MIT
Classifier: Programming Language :: Python :: 3
Classifier: License :: OSI Approved :: MIT License
Classifier: Operating System :: OS Independent
Requires-Python: >=3.10
